[
null,
{"id":1,"members":[{"enemyId":1,"x":336,"y":436,"hidden":false},{"enemyId":1,"x":480,"y":436,"hidden":false}],"name":"Bat*2","pages":[{"conditions":{"actorHp":50,"actorId":1,"actorValid":false,"enemyHp":50,"enemyIndex":0,"enemyValid":false,"switchId":1,"switchValid":false,"turnA":0,"turnB":0,"turnEnding":false,"turnValid":false},"list":[{"code":0,"indent":0,"parameters":[]}],"span":0}]},
{"id":2,"members":[{"enemyId":2,"x":337,"y":436,"hidden":false},{"enemyId":2,"x":480,"y":436,"hidden":false}],"name":"Slime*2","pages":[{"conditions":{"actorHp":50,"actorId":1,"actorValid":false,"enemyHp":50,"enemyIndex":0,"enemyValid":false,"switchId":1,"switchValid":false,"turnA":0,"turnB":0,"turnEnding":false,"turnValid":false},"list":[{"code":0,"indent":0,"parameters":[]}],"span":0}]},
{"id":3,"members":[{"enemyId":3,"x":408,"y":436,"hidden":false}],"name":"Orc","pages":[{"conditions":{"actorHp":50,"actorId":1,"actorValid":false,"enemyHp":50,"enemyIndex":0,"enemyValid":false,"switchId":1,"switchValid":false,"turnA":0,"turnB":0,"turnEnding":false,"turnValid":false},"list":[{"code":0,"indent":0,"parameters":[]}],"span":0}]},
{"id":4,"members":[{"enemyId":4,"x":408,"y":436,"hidden":false}],"name":"Minotaur","pages":[{"conditions":{"actorHp":50,"actorId":1,"actorValid":false,"enemyHp":50,"enemyIndex":0,"enemyValid":false,"switchId":1,"switchValid":false,"turnA":0,"turnB":0,"turnEnding":false,"turnValid":true},"list":[{"code":0,"indent":0,"parameters":[]}],"span":1}]},
{"id":5,"members":[{"enemyId":5,"x":260,"y":304,"hidden":false}],"name":"Cupcake Golem","pages":[{"conditions":{"actorHp":0,"actorId":8,"actorValid":true,"enemyHp":100,"enemyIndex":0,"enemyValid":false,"switchId":31,"switchValid":false,"turnA":0,"turnB":1,"turnEnding":false,"turnValid":true},"list":[{"code":0,"indent":0,"parameters":[]}],"span":1}]},
{"id":6,"members":[{"enemyId":7,"x":353,"y":436,"hidden":false},{"enemyId":6,"x":485,"y":436,"hidden":false}],"name":"snake bee","pages":[{"conditions":{"actorHp":50,"actorId":1,"actorValid":false,"enemyHp":50,"enemyIndex":0,"enemyValid":false,"switchId":1,"switchValid":false,"turnA":0,"turnB":0,"turnEnding":false,"turnValid":true},"list":[{"code":0,"indent":0,"parameters":[]}],"span":1}]},
{"id":7,"members":[{"enemyId":8,"x":408,"y":436,"hidden":false}],"name":"spider","pages":[{"conditions":{"actorHp":50,"actorId":1,"actorValid":false,"enemyHp":50,"enemyIndex":0,"enemyValid":false,"switchId":1,"switchValid":false,"turnA":0,"turnB":0,"turnEnding":false,"turnValid":true},"list":[{"code":0,"indent":0,"parameters":[]}],"span":0}]},
{"id":8,"members":[{"enemyId":10,"x":253,"y":364,"hidden":false},{"enemyId":9,"x":111,"y":400,"hidden":false}],"name":"pbnj","pages":[{"conditions":{"actorHp":50,"actorId":1,"actorValid":false,"enemyHp":50,"enemyIndex":0,"enemyValid":false,"switchId":1,"switchValid":false,"turnA":0,"turnB":0,"turnEnding":false,"turnValid":true},"list":[{"code":0,"indent":0,"parameters":[]}],"span":1}]},
{"id":9,"members":[{"enemyId":11,"x":387,"y":370,"hidden":false}],"name":"Mimic","pages":[{"conditions":{"actorHp":50,"actorId":1,"actorValid":false,"enemyHp":50,"enemyIndex":0,"enemyValid":false,"switchId":1,"switchValid":false,"turnA":0,"turnB":0,"turnEnding":false,"turnValid":false},"list":[{"code":0,"indent":0,"parameters":[]}],"span":0}]},
{"id":10,"members":[{"enemyId":12,"x":285,"y":265,"hidden":false}],"name":"zoobat","pages":[{"conditions":{"actorHp":50,"actorId":1,"actorValid":false,"enemyHp":50,"enemyIndex":0,"enemyValid":false,"switchId":1,"switchValid":false,"turnA":0,"turnB":0,"turnEnding":false,"turnValid":false},"list":[{"code":0,"indent":0,"parameters":[]}],"span":0}]},
{"id":11,"members":[{"enemyId":13,"x":177,"y":319,"hidden":false}],"name":"royal mimic","pages":[{"conditions":{"actorHp":50,"actorId":1,"actorValid":false,"enemyHp":50,"enemyIndex":0,"enemyValid":false,"switchId":1,"switchValid":false,"turnA":0,"turnB":0,"turnEnding":false,"turnValid":false},"list":[{"code":0,"indent":0,"parameters":[]}],"span":0}]},
{"id":12,"members":[{"enemyId":6,"x":388,"y":301,"hidden":false},{"enemyId":15,"x":168,"y":444,"hidden":false}],"name":"bee plant","pages":[{"conditions":{"actorHp":50,"actorId":1,"actorValid":false,"enemyHp":50,"enemyIndex":0,"enemyValid":false,"switchId":1,"switchValid":false,"turnA":0,"turnB":0,"turnEnding":false,"turnValid":false},"list":[{"code":0,"indent":0,"parameters":[]}],"span":0}]},
{"id":13,"members":[{"enemyId":16,"x":144,"y":373,"hidden":false},{"enemyId":16,"x":262,"y":433,"hidden":false},{"enemyId":16,"x":387,"y":370,"hidden":false}],"name":"rats","pages":[{"conditions":{"actorHp":50,"actorId":1,"actorValid":false,"enemyHp":50,"enemyIndex":0,"enemyValid":false,"switchId":1,"switchValid":false,"turnA":0,"turnB":0,"turnEnding":false,"turnValid":false},"list":[{"code":0,"indent":0,"parameters":[]}],"span":0}]},
{"id":14,"members":[{"enemyId":17,"x":270,"y":313,"hidden":false}],"name":"tire bones","pages":[{"conditions":{"actorHp":50,"actorId":1,"actorValid":false,"enemyHp":50,"enemyIndex":0,"enemyValid":false,"switchId":1,"switchValid":false,"turnA":0,"turnB":0,"turnEnding":false,"turnValid":false},"list":[{"code":0,"indent":0,"parameters":[]}],"span":0}]},
{"id":15,"members":[{"enemyId":18,"x":273,"y":343,"hidden":false}],"name":"not a creeper","pages":[{"conditions":{"actorHp":50,"actorId":1,"actorValid":false,"enemyHp":50,"enemyIndex":0,"enemyValid":false,"switchId":1,"switchValid":false,"turnA":0,"turnB":0,"turnEnding":false,"turnValid":false},"list":[{"code":0,"indent":0,"parameters":[]}],"span":0}]},
{"id":16,"members":[{"enemyId":19,"x":294,"y":328,"hidden":false}],"name":"gold mimic","pages":[{"conditions":{"actorHp":50,"actorId":1,"actorValid":false,"enemyHp":50,"enemyIndex":0,"enemyValid":false,"switchId":1,"switchValid":false,"turnA":0,"turnB":0,"turnEnding":false,"turnValid":false},"list":[{"code":0,"indent":0,"parameters":[]}],"span":0}]},
{"id":17,"members":[{"enemyId":20,"x":351,"y":376,"hidden":false}],"name":"incream boss","pages":[{"conditions":{"actorHp":0,"actorId":9,"actorValid":true,"enemyHp":50,"enemyIndex":0,"enemyValid":false,"switchId":1,"switchValid":false,"turnA":0,"turnB":0,"turnEnding":false,"turnValid":false},"list":[{"code":117,"indent":0,"parameters":[45]},{"code":0,"indent":0,"parameters":[]}],"span":0}]},
{"id":18,"members":[{"enemyId":22,"x":238,"y":361,"hidden":false},{"enemyId":22,"x":501,"y":361,"hidden":false}],"name":"chocolate slime","pages":[{"conditions":{"actorHp":50,"actorId":1,"actorValid":false,"enemyHp":50,"enemyIndex":0,"enemyValid":false,"switchId":110,"switchValid":false,"turnA":0,"turnB":0,"turnEnding":false,"turnValid":false},"list":[{"code":117,"indent":0,"parameters":[46]},{"code":0,"indent":0,"parameters":[]}],"span":2}]},
{"id":19,"members":[{"enemyId":21,"x":276,"y":298,"hidden":false},{"enemyId":21,"x":556,"y":367,"hidden":false}],"name":"ice wing mobs","pages":[{"conditions":{"actorHp":50,"actorId":1,"actorValid":false,"enemyHp":50,"enemyIndex":0,"enemyValid":false,"switchId":110,"switchValid":false,"turnA":0,"turnB":0,"turnEnding":false,"turnValid":false},"list":[{"code":117,"indent":0,"parameters":[46]},{"code":0,"indent":0,"parameters":[]}],"span":2}]},
{"id":20,"members":[{"enemyId":23,"x":408,"y":436,"hidden":false}],"name":"metal slime","pages":[{"conditions":{"actorHp":50,"actorId":1,"actorValid":false,"enemyHp":50,"enemyIndex":0,"enemyValid":false,"switchId":110,"switchValid":false,"turnA":0,"turnB":0,"turnEnding":false,"turnValid":false},"list":[{"code":117,"indent":0,"parameters":[46]},{"code":0,"indent":0,"parameters":[]}],"span":2}]},
{"id":21,"members":[{"enemyId":3,"x":140,"y":436,"hidden":false},{"enemyId":3,"x":153,"y":436,"hidden":false},{"enemyId":3,"x":166,"y":436,"hidden":false},{"enemyId":3,"x":179,"y":436,"hidden":false},{"enemyId":4,"x":248,"y":436,"hidden":false},{"enemyId":4,"x":372,"y":436,"hidden":false},{"enemyId":4,"x":496,"y":436,"hidden":false},{"enemyId":4,"x":621,"y":436,"hidden":false}],"name":"","pages":[{"conditions":{"actorHp":50,"actorId":1,"actorValid":false,"enemyHp":50,"enemyIndex":0,"enemyValid":false,"switchId":1,"switchValid":false,"turnA":0,"turnB":0,"turnEnding":false,"turnValid":false},"list":[{"code":0,"indent":0,"parameters":[]}],"span":0}]},
{"id":22,"members":[{"enemyId":24,"x":384,"y":253,"hidden":false},{"enemyId":25,"x":159,"y":397,"hidden":false},{"enemyId":25,"x":615,"y":382,"hidden":false}],"name":"cupecake boss","pages":[{"conditions":{"actorHp":50,"actorId":1,"actorValid":false,"enemyHp":50,"enemyIndex":0,"enemyValid":false,"switchId":1,"switchValid":false,"turnA":0,"turnB":0,"turnEnding":false,"turnValid":false},"list":[{"code":0,"indent":0,"parameters":[]}],"span":0}]},
{"id":23,"members":[{"enemyId":37,"x":280,"y":436,"hidden":false},{"enemyId":26,"x":344,"y":343,"hidden":false}],"name":"Mastiphigia","pages":[{"conditions":{"actorHp":50,"actorId":1,"actorValid":false,"enemyHp":50,"enemyIndex":0,"enemyValid":false,"switchId":1,"switchValid":false,"turnA":0,"turnB":0,"turnEnding":false,"turnValid":false},"list":[{"code":0,"indent":0,"parameters":[]}],"span":0}]},
{"id":24,"members":[{"enemyId":27,"x":147,"y":286,"hidden":false},{"enemyId":27,"x":345,"y":319,"hidden":false}],"name":"snow mobs","pages":[{"conditions":{"actorHp":50,"actorId":1,"actorValid":false,"enemyHp":50,"enemyIndex":0,"enemyValid":false,"switchId":1,"switchValid":false,"turnA":0,"turnB":0,"turnEnding":false,"turnValid":false},"list":[{"code":0,"indent":0,"parameters":[]}],"span":0}]},
{"id":25,"members":[{"enemyId":29,"x":117,"y":444,"hidden":false},{"enemyId":29,"x":498,"y":438,"hidden":false},{"enemyId":28,"x":295,"y":370,"hidden":false}],"name":"ruins hard mob","pages":[{"conditions":{"actorHp":50,"actorId":1,"actorValid":false,"enemyHp":50,"enemyIndex":0,"enemyValid":false,"switchId":1,"switchValid":false,"turnA":0,"turnB":0,"turnEnding":false,"turnValid":false},"list":[{"code":0,"indent":0,"parameters":[]}],"span":0}]},
{"id":26,"members":[{"enemyId":28,"x":408,"y":436,"hidden":false}],"name":"stone warden","pages":[{"conditions":{"actorHp":50,"actorId":1,"actorValid":false,"enemyHp":50,"enemyIndex":0,"enemyValid":false,"switchId":1,"switchValid":false,"turnA":0,"turnB":0,"turnEnding":false,"turnValid":false},"list":[{"code":0,"indent":0,"parameters":[]}],"span":0}]},
{"id":27,"members":[{"enemyId":29,"x":166,"y":370,"hidden":false},{"enemyId":29,"x":327,"y":298,"hidden":false}],"name":"lost soul","pages":[{"conditions":{"actorHp":50,"actorId":1,"actorValid":false,"enemyHp":50,"enemyIndex":0,"enemyValid":false,"switchId":1,"switchValid":false,"turnA":0,"turnB":0,"turnEnding":false,"turnValid":false},"list":[{"code":0,"indent":0,"parameters":[]}],"span":0}]},
{"id":28,"members":[{"enemyId":29,"x":258,"y":364,"hidden":false}],"name":"lost soul fress","pages":[{"conditions":{"actorHp":50,"actorId":1,"actorValid":false,"enemyHp":50,"enemyIndex":0,"enemyValid":false,"switchId":1,"switchValid":false,"turnA":0,"turnB":0,"turnEnding":false,"turnValid":false},"list":[{"code":0,"indent":0,"parameters":[]}],"span":0}]},
{"id":29,"members":[{"enemyId":30,"x":96,"y":241,"hidden":false},{"enemyId":30,"x":501,"y":322,"hidden":false}],"name":"imps moutain","pages":[{"conditions":{"actorHp":50,"actorId":1,"actorValid":false,"enemyHp":50,"enemyIndex":0,"enemyValid":false,"switchId":1,"switchValid":false,"turnA":0,"turnB":0,"turnEnding":false,"turnValid":false},"list":[{"code":0,"indent":0,"parameters":[]}],"span":0}]},
{"id":30,"members":[{"enemyId":27,"x":111,"y":211,"hidden":false},{"enemyId":29,"x":273,"y":406,"hidden":false},{"enemyId":30,"x":501,"y":268,"hidden":false}],"name":"snowmobs 2","pages":[{"conditions":{"actorHp":50,"actorId":1,"actorValid":false,"enemyHp":50,"enemyIndex":0,"enemyValid":false,"switchId":1,"switchValid":false,"turnA":0,"turnB":0,"turnEnding":false,"turnValid":false},"list":[{"code":0,"indent":0,"parameters":[]}],"span":0}]},
{"id":31,"members":[{"enemyId":31,"x":339,"y":340,"hidden":false}],"name":"Mastiphigia","pages":[{"conditions":{"actorHp":50,"actorId":1,"actorValid":false,"enemyHp":50,"enemyIndex":0,"enemyValid":false,"switchId":1,"switchValid":false,"turnA":0,"turnB":0,"turnEnding":false,"turnValid":false},"list":[{"code":0,"indent":0,"parameters":[]}],"span":0}]},
{"id":32,"members":[{"enemyId":32,"x":408,"y":436,"hidden":false}],"name":"Cluckdragon","pages":[{"conditions":{"actorHp":50,"actorId":1,"actorValid":false,"enemyHp":50,"enemyIndex":0,"enemyValid":false,"switchId":1,"switchValid":false,"turnA":0,"turnB":0,"turnEnding":false,"turnValid":false},"list":[{"code":0,"indent":0,"parameters":[]}],"span":0}]},
{"id":33,"members":[{"enemyId":32,"x":274,"y":355,"hidden":false},{"enemyId":32,"x":417,"y":444,"hidden":false}],"name":"Cluckdragons","pages":[{"conditions":{"actorHp":50,"actorId":1,"actorValid":false,"enemyHp":50,"enemyIndex":0,"enemyValid":false,"switchId":1,"switchValid":false,"turnA":0,"turnB":0,"turnEnding":false,"turnValid":false},"list":[{"code":0,"indent":0,"parameters":[]}],"span":0}]},
{"id":34,"members":[{"enemyId":33,"x":218,"y":394,"hidden":false},{"enemyId":33,"x":437,"y":322,"hidden":false}],"name":"test","pages":[{"conditions":{"actorHp":50,"actorId":1,"actorValid":false,"enemyHp":50,"enemyIndex":0,"enemyValid":false,"switchId":1,"switchValid":false,"turnA":1,"turnB":1,"turnEnding":true,"turnValid":true},"list":[{"code":117,"indent":0,"parameters":[22]},{"code":0,"indent":0,"parameters":[]}],"span":2}]},
{"id":35,"members":[{"enemyId":7,"x":90,"y":340,"hidden":false},{"enemyId":9,"x":243,"y":247,"hidden":false},{"enemyId":10,"x":369,"y":337,"hidden":false},{"enemyId":8,"x":210,"y":444,"hidden":false},{"enemyId":21,"x":495,"y":268,"hidden":false},{"enemyId":21,"x":612,"y":436,"hidden":false},{"enemyId":21,"x":420,"y":444,"hidden":false}],"name":"","pages":[{"conditions":{"actorHp":50,"actorId":1,"actorValid":false,"enemyHp":50,"enemyIndex":0,"enemyValid":false,"switchId":1,"switchValid":false,"turnA":0,"turnB":0,"turnEnding":false,"turnValid":false},"list":[{"code":0,"indent":0,"parameters":[]}],"span":0}]},
{"id":36,"members":[{"enemyId":38,"x":408,"y":436,"hidden":false}],"name":"test","pages":[{"conditions":{"actorHp":50,"actorId":1,"actorValid":false,"enemyHp":50,"enemyIndex":0,"enemyValid":false,"switchId":1,"switchValid":false,"turnA":0,"turnB":0,"turnEnding":false,"turnValid":false},"list":[{"code":0,"indent":0,"parameters":[]}],"span":0}]},
{"id":37,"members":[{"enemyId":6,"x":517,"y":375,"hidden":false},{"enemyId":6,"x":159,"y":403,"hidden":false},{"enemyId":6,"x":305,"y":352,"hidden":false},{"enemyId":6,"x":199,"y":235,"hidden":false},{"enemyId":6,"x":398,"y":444,"hidden":false},{"enemyId":6,"x":655,"y":394,"hidden":false},{"enemyId":6,"x":399,"y":274,"hidden":false},{"enemyId":6,"x":611,"y":226,"hidden":false}],"name":"","pages":[{"conditions":{"actorHp":50,"actorId":1,"actorValid":false,"enemyHp":50,"enemyIndex":0,"enemyValid":false,"switchId":1,"switchValid":false,"turnA":0,"turnB":0,"turnEnding":false,"turnValid":false},"list":[{"code":0,"indent":0,"parameters":[]}],"span":0}]},
{"id":38,"members":[{"enemyId":39,"x":285,"y":349,"hidden":false}],"name":"sbot","pages":[{"conditions":{"actorHp":50,"actorId":1,"actorValid":false,"enemyHp":50,"enemyIndex":0,"enemyValid":false,"switchId":1,"switchValid":false,"turnA":0,"turnB":0,"turnEnding":false,"turnValid":false},"list":[{"code":0,"indent":0,"parameters":[]}],"span":0}]},
{"id":39,"members":[{"enemyId":39,"x":103,"y":355,"hidden":false},{"enemyId":39,"x":524,"y":301,"hidden":false},{"enemyId":40,"x":340,"y":441,"hidden":false}],"name":"skbot","pages":[{"conditions":{"actorHp":50,"actorId":1,"actorValid":false,"enemyHp":50,"enemyIndex":0,"enemyValid":false,"switchId":1,"switchValid":false,"turnA":0,"turnB":0,"turnEnding":false,"turnValid":false},"list":[{"code":0,"indent":0,"parameters":[]}],"span":0}]},
{"id":40,"members":[{"enemyId":41,"x":210,"y":328,"hidden":false}],"name":"msbot","pages":[{"conditions":{"actorHp":50,"actorId":1,"actorValid":false,"enemyHp":50,"enemyIndex":0,"enemyValid":false,"switchId":1,"switchValid":false,"turnA":0,"turnB":0,"turnEnding":false,"turnValid":false},"list":[{"code":0,"indent":0,"parameters":[]}],"span":0}]},
{"id":41,"members":[{"enemyId":42,"x":360,"y":358,"hidden":false}],"name":"Vivant","pages":[{"conditions":{"actorHp":50,"actorId":1,"actorValid":false,"enemyHp":50,"enemyIndex":0,"enemyValid":true,"switchId":1,"switchValid":false,"turnA":0,"turnB":0,"turnEnding":false,"turnValid":false},"list":[{"code":117,"indent":0,"parameters":[42]},{"code":0,"indent":0,"parameters":[]}],"span":1}]},
{"id":42,"members":[{"enemyId":43,"x":363,"y":394,"hidden":false},{"enemyId":44,"x":141,"y":229,"hidden":true},{"enemyId":44,"x":594,"y":238,"hidden":true}],"name":"viant","pages":[{"conditions":{"actorHp":50,"actorId":1,"actorValid":false,"enemyHp":50,"enemyIndex":0,"enemyValid":true,"switchId":1,"switchValid":false,"turnA":0,"turnB":0,"turnEnding":false,"turnValid":false},"list":[{"code":117,"indent":0,"parameters":[42]},{"code":0,"indent":0,"parameters":[]}],"span":0}]},
{"id":43,"members":[],"name":"","pages":[{"conditions":{"actorHp":50,"actorId":1,"actorValid":false,"enemyHp":50,"enemyIndex":0,"enemyValid":false,"switchId":1,"switchValid":false,"turnA":0,"turnB":0,"turnEnding":false,"turnValid":false},"list":[{"code":0,"indent":0,"parameters":[]}],"span":0}]},
{"id":44,"members":[],"name":"","pages":[{"conditions":{"actorHp":50,"actorId":1,"actorValid":false,"enemyHp":50,"enemyIndex":0,"enemyValid":false,"switchId":1,"switchValid":false,"turnA":0,"turnB":0,"turnEnding":false,"turnValid":false},"list":[{"code":0,"indent":0,"parameters":[]}],"span":0}]},
{"id":45,"members":[],"name":"","pages":[{"conditions":{"actorHp":50,"actorId":1,"actorValid":false,"enemyHp":50,"enemyIndex":0,"enemyValid":false,"switchId":1,"switchValid":false,"turnA":0,"turnB":0,"turnEnding":false,"turnValid":false},"list":[{"code":0,"indent":0,"parameters":[]}],"span":0}]},
{"id":46,"members":[],"name":"","pages":[{"conditions":{"actorHp":50,"actorId":1,"actorValid":false,"enemyHp":50,"enemyIndex":0,"enemyValid":false,"switchId":1,"switchValid":false,"turnA":0,"turnB":0,"turnEnding":false,"turnValid":false},"list":[{"code":0,"indent":0,"parameters":[]}],"span":0}]},
{"id":47,"members":[],"name":"","pages":[{"conditions":{"actorHp":50,"actorId":1,"actorValid":false,"enemyHp":50,"enemyIndex":0,"enemyValid":false,"switchId":1,"switchValid":false,"turnA":0,"turnB":0,"turnEnding":false,"turnValid":false},"list":[{"code":0,"indent":0,"parameters":[]}],"span":0}]},
{"id":48,"members":[],"name":"","pages":[{"conditions":{"actorHp":50,"actorId":1,"actorValid":false,"enemyHp":50,"enemyIndex":0,"enemyValid":false,"switchId":1,"switchValid":false,"turnA":0,"turnB":0,"turnEnding":false,"turnValid":false},"list":[{"code":0,"indent":0,"parameters":[]}],"span":0}]},
{"id":49,"members":[],"name":"","pages":[{"conditions":{"actorHp":50,"actorId":1,"actorValid":false,"enemyHp":50,"enemyIndex":0,"enemyValid":false,"switchId":1,"switchValid":false,"turnA":0,"turnB":0,"turnEnding":false,"turnValid":false},"list":[{"code":0,"indent":0,"parameters":[]}],"span":0}]},
{"id":50,"members":[],"name":"","pages":[{"conditions":{"actorHp":50,"actorId":1,"actorValid":false,"enemyHp":50,"enemyIndex":0,"enemyValid":false,"switchId":1,"switchValid":false,"turnA":0,"turnB":0,"turnEnding":false,"turnValid":false},"list":[{"code":0,"indent":0,"parameters":[]}],"span":0}]},
{"id":51,"members":[],"name":"","pages":[{"conditions":{"actorHp":50,"actorId":1,"actorValid":false,"enemyHp":50,"enemyIndex":0,"enemyValid":false,"switchId":1,"switchValid":false,"turnA":0,"turnB":0,"turnEnding":false,"turnValid":false},"list":[{"code":0,"indent":0,"parameters":[]}],"span":0}]},
{"id":52,"members":[],"name":"","pages":[{"conditions":{"actorHp":50,"actorId":1,"actorValid":false,"enemyHp":50,"enemyIndex":0,"enemyValid":false,"switchId":1,"switchValid":false,"turnA":0,"turnB":0,"turnEnding":false,"turnValid":false},"list":[{"code":0,"indent":0,"parameters":[]}],"span":0}]},
{"id":53,"members":[],"name":"","pages":[{"conditions":{"actorHp":50,"actorId":1,"actorValid":false,"enemyHp":50,"enemyIndex":0,"enemyValid":false,"switchId":1,"switchValid":false,"turnA":0,"turnB":0,"turnEnding":false,"turnValid":false},"list":[{"code":0,"indent":0,"parameters":[]}],"span":0}]},
{"id":54,"members":[],"name":"","pages":[{"conditions":{"actorHp":50,"actorId":1,"actorValid":false,"enemyHp":50,"enemyIndex":0,"enemyValid":false,"switchId":1,"switchValid":false,"turnA":0,"turnB":0,"turnEnding":false,"turnValid":false},"list":[{"code":0,"indent":0,"parameters":[]}],"span":0}]},
{"id":55,"members":[],"name":"","pages":[{"conditions":{"actorHp":50,"actorId":1,"actorValid":false,"enemyHp":50,"enemyIndex":0,"enemyValid":false,"switchId":1,"switchValid":false,"turnA":0,"turnB":0,"turnEnding":false,"turnValid":false},"list":[{"code":0,"indent":0,"parameters":[]}],"span":0}]},
{"id":56,"members":[],"name":"","pages":[{"conditions":{"actorHp":50,"actorId":1,"actorValid":false,"enemyHp":50,"enemyIndex":0,"enemyValid":false,"switchId":1,"switchValid":false,"turnA":0,"turnB":0,"turnEnding":false,"turnValid":false},"list":[{"code":0,"indent":0,"parameters":[]}],"span":0}]},
{"id":57,"members":[],"name":"","pages":[{"conditions":{"actorHp":50,"actorId":1,"actorValid":false,"enemyHp":50,"enemyIndex":0,"enemyValid":false,"switchId":1,"switchValid":false,"turnA":0,"turnB":0,"turnEnding":false,"turnValid":false},"list":[{"code":0,"indent":0,"parameters":[]}],"span":0}]},
{"id":58,"members":[],"name":"","pages":[{"conditions":{"actorHp":50,"actorId":1,"actorValid":false,"enemyHp":50,"enemyIndex":0,"enemyValid":false,"switchId":1,"switchValid":false,"turnA":0,"turnB":0,"turnEnding":false,"turnValid":false},"list":[{"code":0,"indent":0,"parameters":[]}],"span":0}]},
{"id":59,"members":[],"name":"","pages":[{"conditions":{"actorHp":50,"actorId":1,"actorValid":false,"enemyHp":50,"enemyIndex":0,"enemyValid":false,"switchId":1,"switchValid":false,"turnA":0,"turnB":0,"turnEnding":false,"turnValid":false},"list":[{"code":0,"indent":0,"parameters":[]}],"span":0}]},
{"id":60,"members":[],"name":"","pages":[{"conditions":{"actorHp":50,"actorId":1,"actorValid":false,"enemyHp":50,"enemyIndex":0,"enemyValid":false,"switchId":1,"switchValid":false,"turnA":0,"turnB":0,"turnEnding":false,"turnValid":false},"list":[{"code":0,"indent":0,"parameters":[]}],"span":0}]},
{"id":61,"members":[],"name":"","pages":[{"conditions":{"actorHp":50,"actorId":1,"actorValid":false,"enemyHp":50,"enemyIndex":0,"enemyValid":false,"switchId":1,"switchValid":false,"turnA":0,"turnB":0,"turnEnding":false,"turnValid":false},"list":[{"code":0,"indent":0,"parameters":[]}],"span":0}]},
{"id":62,"members":[],"name":"","pages":[{"conditions":{"actorHp":50,"actorId":1,"actorValid":false,"enemyHp":50,"enemyIndex":0,"enemyValid":false,"switchId":1,"switchValid":false,"turnA":0,"turnB":0,"turnEnding":false,"turnValid":false},"list":[{"code":0,"indent":0,"parameters":[]}],"span":0}]},
{"id":63,"members":[],"name":"","pages":[{"conditions":{"actorHp":50,"actorId":1,"actorValid":false,"enemyHp":50,"enemyIndex":0,"enemyValid":false,"switchId":1,"switchValid":false,"turnA":0,"turnB":0,"turnEnding":false,"turnValid":false},"list":[{"code":0,"indent":0,"parameters":[]}],"span":0}]},
{"id":64,"members":[],"name":"","pages":[{"conditions":{"actorHp":50,"actorId":1,"actorValid":false,"enemyHp":50,"enemyIndex":0,"enemyValid":false,"switchId":1,"switchValid":false,"turnA":0,"turnB":0,"turnEnding":false,"turnValid":false},"list":[{"code":0,"indent":0,"parameters":[]}],"span":0}]},
{"id":65,"members":[],"name":"","pages":[{"conditions":{"actorHp":50,"actorId":1,"actorValid":false,"enemyHp":50,"enemyIndex":0,"enemyValid":false,"switchId":1,"switchValid":false,"turnA":0,"turnB":0,"turnEnding":false,"turnValid":false},"list":[{"code":0,"indent":0,"parameters":[]}],"span":0}]},
{"id":66,"members":[],"name":"","pages":[{"conditions":{"actorHp":50,"actorId":1,"actorValid":false,"enemyHp":50,"enemyIndex":0,"enemyValid":false,"switchId":1,"switchValid":false,"turnA":0,"turnB":0,"turnEnding":false,"turnValid":false},"list":[{"code":0,"indent":0,"parameters":[]}],"span":0}]},
{"id":67,"members":[],"name":"","pages":[{"conditions":{"actorHp":50,"actorId":1,"actorValid":false,"enemyHp":50,"enemyIndex":0,"enemyValid":false,"switchId":1,"switchValid":false,"turnA":0,"turnB":0,"turnEnding":false,"turnValid":false},"list":[{"code":0,"indent":0,"parameters":[]}],"span":0}]},
{"id":68,"members":[],"name":"","pages":[{"conditions":{"actorHp":50,"actorId":1,"actorValid":false,"enemyHp":50,"enemyIndex":0,"enemyValid":false,"switchId":1,"switchValid":false,"turnA":0,"turnB":0,"turnEnding":false,"turnValid":false},"list":[{"code":0,"indent":0,"parameters":[]}],"span":0}]},
{"id":69,"members":[],"name":"","pages":[{"conditions":{"actorHp":50,"actorId":1,"actorValid":false,"enemyHp":50,"enemyIndex":0,"enemyValid":false,"switchId":1,"switchValid":false,"turnA":0,"turnB":0,"turnEnding":false,"turnValid":false},"list":[{"code":0,"indent":0,"parameters":[]}],"span":0}]},
{"id":70,"members":[],"name":"","pages":[{"conditions":{"actorHp":50,"actorId":1,"actorValid":false,"enemyHp":50,"enemyIndex":0,"enemyValid":false,"switchId":1,"switchValid":false,"turnA":0,"turnB":0,"turnEnding":false,"turnValid":false},"list":[{"code":0,"indent":0,"parameters":[]}],"span":0}]},
{"id":71,"members":[],"name":"","pages":[{"conditions":{"actorHp":50,"actorId":1,"actorValid":false,"enemyHp":50,"enemyIndex":0,"enemyValid":false,"switchId":1,"switchValid":false,"turnA":0,"turnB":0,"turnEnding":false,"turnValid":false},"list":[{"code":0,"indent":0,"parameters":[]}],"span":0}]},
{"id":72,"members":[],"name":"","pages":[{"conditions":{"actorHp":50,"actorId":1,"actorValid":false,"enemyHp":50,"enemyIndex":0,"enemyValid":false,"switchId":1,"switchValid":false,"turnA":0,"turnB":0,"turnEnding":false,"turnValid":false},"list":[{"code":0,"indent":0,"parameters":[]}],"span":0}]},
{"id":73,"members":[],"name":"","pages":[{"conditions":{"actorHp":50,"actorId":1,"actorValid":false,"enemyHp":50,"enemyIndex":0,"enemyValid":false,"switchId":1,"switchValid":false,"turnA":0,"turnB":0,"turnEnding":false,"turnValid":false},"list":[{"code":0,"indent":0,"parameters":[]}],"span":0}]},
{"id":74,"members":[],"name":"","pages":[{"conditions":{"actorHp":50,"actorId":1,"actorValid":false,"enemyHp":50,"enemyIndex":0,"enemyValid":false,"switchId":1,"switchValid":false,"turnA":0,"turnB":0,"turnEnding":false,"turnValid":false},"list":[{"code":0,"indent":0,"parameters":[]}],"span":0}]},
{"id":75,"members":[],"name":"","pages":[{"conditions":{"actorHp":50,"actorId":1,"actorValid":false,"enemyHp":50,"enemyIndex":0,"enemyValid":false,"switchId":1,"switchValid":false,"turnA":0,"turnB":0,"turnEnding":false,"turnValid":false},"list":[{"code":0,"indent":0,"parameters":[]}],"span":0}]},
{"id":76,"members":[],"name":"","pages":[{"conditions":{"actorHp":50,"actorId":1,"actorValid":false,"enemyHp":50,"enemyIndex":0,"enemyValid":false,"switchId":1,"switchValid":false,"turnA":0,"turnB":0,"turnEnding":false,"turnValid":false},"list":[{"code":0,"indent":0,"parameters":[]}],"span":0}]},
{"id":77,"members":[],"name":"","pages":[{"conditions":{"actorHp":50,"actorId":1,"actorValid":false,"enemyHp":50,"enemyIndex":0,"enemyValid":false,"switchId":1,"switchValid":false,"turnA":0,"turnB":0,"turnEnding":false,"turnValid":false},"list":[{"code":0,"indent":0,"parameters":[]}],"span":0}]},
{"id":78,"members":[],"name":"","pages":[{"conditions":{"actorHp":50,"actorId":1,"actorValid":false,"enemyHp":50,"enemyIndex":0,"enemyValid":false,"switchId":1,"switchValid":false,"turnA":0,"turnB":0,"turnEnding":false,"turnValid":false},"list":[{"code":0,"indent":0,"parameters":[]}],"span":0}]},
{"id":79,"members":[],"name":"","pages":[{"conditions":{"actorHp":50,"actorId":1,"actorValid":false,"enemyHp":50,"enemyIndex":0,"enemyValid":false,"switchId":1,"switchValid":false,"turnA":0,"turnB":0,"turnEnding":false,"turnValid":false},"list":[{"code":0,"indent":0,"parameters":[]}],"span":0}]},
{"id":80,"members":[],"name":"","pages":[{"conditions":{"actorHp":50,"actorId":1,"actorValid":false,"enemyHp":50,"enemyIndex":0,"enemyValid":false,"switchId":1,"switchValid":false,"turnA":0,"turnB":0,"turnEnding":false,"turnValid":false},"list":[{"code":0,"indent":0,"parameters":[]}],"span":0}]},
{"id":81,"members":[],"name":"","pages":[{"conditions":{"actorHp":50,"actorId":1,"actorValid":false,"enemyHp":50,"enemyIndex":0,"enemyValid":false,"switchId":1,"switchValid":false,"turnA":0,"turnB":0,"turnEnding":false,"turnValid":false},"list":[{"code":0,"indent":0,"parameters":[]}],"span":0}]},
{"id":82,"members":[],"name":"","pages":[{"conditions":{"actorHp":50,"actorId":1,"actorValid":false,"enemyHp":50,"enemyIndex":0,"enemyValid":false,"switchId":1,"switchValid":false,"turnA":0,"turnB":0,"turnEnding":false,"turnValid":false},"list":[{"code":0,"indent":0,"parameters":[]}],"span":0}]},
{"id":83,"members":[],"name":"","pages":[{"conditions":{"actorHp":50,"actorId":1,"actorValid":false,"enemyHp":50,"enemyIndex":0,"enemyValid":false,"switchId":1,"switchValid":false,"turnA":0,"turnB":0,"turnEnding":false,"turnValid":false},"list":[{"code":0,"indent":0,"parameters":[]}],"span":0}]},
{"id":84,"members":[],"name":"","pages":[{"conditions":{"actorHp":50,"actorId":1,"actorValid":false,"enemyHp":50,"enemyIndex":0,"enemyValid":false,"switchId":1,"switchValid":false,"turnA":0,"turnB":0,"turnEnding":false,"turnValid":false},"list":[{"code":0,"indent":0,"parameters":[]}],"span":0}]},
{"id":85,"members":[],"name":"","pages":[{"conditions":{"actorHp":50,"actorId":1,"actorValid":false,"enemyHp":50,"enemyIndex":0,"enemyValid":false,"switchId":1,"switchValid":false,"turnA":0,"turnB":0,"turnEnding":false,"turnValid":false},"list":[{"code":0,"indent":0,"parameters":[]}],"span":0}]},
{"id":86,"members":[],"name":"","pages":[{"conditions":{"actorHp":50,"actorId":1,"actorValid":false,"enemyHp":50,"enemyIndex":0,"enemyValid":false,"switchId":1,"switchValid":false,"turnA":0,"turnB":0,"turnEnding":false,"turnValid":false},"list":[{"code":0,"indent":0,"parameters":[]}],"span":0}]},
{"id":87,"members":[],"name":"","pages":[{"conditions":{"actorHp":50,"actorId":1,"actorValid":false,"enemyHp":50,"enemyIndex":0,"enemyValid":false,"switchId":1,"switchValid":false,"turnA":0,"turnB":0,"turnEnding":false,"turnValid":false},"list":[{"code":0,"indent":0,"parameters":[]}],"span":0}]},
{"id":88,"members":[],"name":"","pages":[{"conditions":{"actorHp":50,"actorId":1,"actorValid":false,"enemyHp":50,"enemyIndex":0,"enemyValid":false,"switchId":1,"switchValid":false,"turnA":0,"turnB":0,"turnEnding":false,"turnValid":false},"list":[{"code":0,"indent":0,"parameters":[]}],"span":0}]},
{"id":89,"members":[],"name":"","pages":[{"conditions":{"actorHp":50,"actorId":1,"actorValid":false,"enemyHp":50,"enemyIndex":0,"enemyValid":false,"switchId":1,"switchValid":false,"turnA":0,"turnB":0,"turnEnding":false,"turnValid":false},"list":[{"code":0,"indent":0,"parameters":[]}],"span":0}]},
{"id":90,"members":[],"name":"","pages":[{"conditions":{"actorHp":50,"actorId":1,"actorValid":false,"enemyHp":50,"enemyIndex":0,"enemyValid":false,"switchId":1,"switchValid":false,"turnA":0,"turnB":0,"turnEnding":false,"turnValid":false},"list":[{"code":0,"indent":0,"parameters":[]}],"span":0}]},
{"id":91,"members":[],"name":"","pages":[{"conditions":{"actorHp":50,"actorId":1,"actorValid":false,"enemyHp":50,"enemyIndex":0,"enemyValid":false,"switchId":1,"switchValid":false,"turnA":0,"turnB":0,"turnEnding":false,"turnValid":false},"list":[{"code":0,"indent":0,"parameters":[]}],"span":0}]},
{"id":92,"members":[],"name":"","pages":[{"conditions":{"actorHp":50,"actorId":1,"actorValid":false,"enemyHp":50,"enemyIndex":0,"enemyValid":false,"switchId":1,"switchValid":false,"turnA":0,"turnB":0,"turnEnding":false,"turnValid":false},"list":[{"code":0,"indent":0,"parameters":[]}],"span":0}]},
{"id":93,"members":[],"name":"","pages":[{"conditions":{"actorHp":50,"actorId":1,"actorValid":false,"enemyHp":50,"enemyIndex":0,"enemyValid":false,"switchId":1,"switchValid":false,"turnA":0,"turnB":0,"turnEnding":false,"turnValid":false},"list":[{"code":0,"indent":0,"parameters":[]}],"span":0}]},
{"id":94,"members":[],"name":"","pages":[{"conditions":{"actorHp":50,"actorId":1,"actorValid":false,"enemyHp":50,"enemyIndex":0,"enemyValid":false,"switchId":1,"switchValid":false,"turnA":0,"turnB":0,"turnEnding":false,"turnValid":false},"list":[{"code":0,"indent":0,"parameters":[]}],"span":0}]},
{"id":95,"members":[],"name":"","pages":[{"conditions":{"actorHp":50,"actorId":1,"actorValid":false,"enemyHp":50,"enemyIndex":0,"enemyValid":false,"switchId":1,"switchValid":false,"turnA":0,"turnB":0,"turnEnding":false,"turnValid":false},"list":[{"code":0,"indent":0,"parameters":[]}],"span":0}]},
{"id":96,"members":[],"name":"","pages":[{"conditions":{"actorHp":50,"actorId":1,"actorValid":false,"enemyHp":50,"enemyIndex":0,"enemyValid":false,"switchId":1,"switchValid":false,"turnA":0,"turnB":0,"turnEnding":false,"turnValid":false},"list":[{"code":0,"indent":0,"parameters":[]}],"span":0}]},
{"id":97,"members":[],"name":"","pages":[{"conditions":{"actorHp":50,"actorId":1,"actorValid":false,"enemyHp":50,"enemyIndex":0,"enemyValid":false,"switchId":1,"switchValid":false,"turnA":0,"turnB":0,"turnEnding":false,"turnValid":false},"list":[{"code":0,"indent":0,"parameters":[]}],"span":0}]},
{"id":98,"members":[],"name":"","pages":[{"conditions":{"actorHp":50,"actorId":1,"actorValid":false,"enemyHp":50,"enemyIndex":0,"enemyValid":false,"switchId":1,"switchValid":false,"turnA":0,"turnB":0,"turnEnding":false,"turnValid":false},"list":[{"code":0,"indent":0,"parameters":[]}],"span":0}]},
{"id":99,"members":[],"name":"","pages":[{"conditions":{"actorHp":50,"actorId":1,"actorValid":false,"enemyHp":50,"enemyIndex":0,"enemyValid":false,"switchId":1,"switchValid":false,"turnA":0,"turnB":0,"turnEnding":false,"turnValid":false},"list":[{"code":0,"indent":0,"parameters":[]}],"span":0}]},
{"id":100,"members":[],"name":"","pages":[{"conditions":{"actorHp":50,"actorId":1,"actorValid":false,"enemyHp":50,"enemyIndex":0,"enemyValid":false,"switchId":1,"switchValid":false,"turnA":0,"turnB":0,"turnEnding":false,"turnValid":false},"list":[{"code":0,"indent":0,"parameters":[]}],"span":0}]}
]